fastapi_simple_crud/__init__.py
fastapi_simple_crud/routing.py
fastapi_simple_crud/simpleCRUD.py
fastapi_simple_crud/dependencies/__init__.py
fastapi_simple_crud/dependencies/log.py
fastapi_simple_crud/dependencies/status.py
fastapi_simple_crud/dependencies/utility.py
fastapi_simple_crud/dependencies/utils.py
fastapi_simple_crud-0.1.6.dist-info/LICENSE
fastapi_simple_crud-0.1.6.dist-info/METADATA
fastapi_simple_crud-0.1.6.dist-info/WHEEL
fastapi_simple_crud-0.1.6.dist-info/top_level.txt
fastapi_simple_crud-0.1.6.dist-info/RECORD
