Metadata-Version: 2.1
Name: fastapi-simple-crud
Version: 0.1.6
Summary: Generate CRUD routers for you schema in a simple way
Home-page: UNKNOWN
Author: danangjoyoo (Agus Danangjoyo)
Author-email: <agus.danangjoyo.blog@gmail.com>
License: UNKNOWN
Keywords: fastapi,crud,restful,routing,router,generator,aiosqlite
Platform: UNKNOWN
Classifier: Development Status :: 3 - Alpha
Classifier: Intended Audience :: Developers
Classifier: Programming Language :: Python :: 3 :: Only
Classifier: Programming Language :: Python :: 3.8
Classifier: Environment :: Web Environment
Classifier: Operating System :: OS Independent
Classifier: Typing :: Typed
